sgp4-2.25.dist-info/RECORD
sgp4-2.25.dist-info/WHEEL
sgp4-2.25.dist-info/top_level.txt
sgp4-2.25.dist-info/METADATA
sgp4-2.25.dist-info/licenses/LICENSE
sgp4/functions.py
sgp4/wrapper.py
sgp4/sample_omm.csv
sgp4/SGP4-VER.TLE
sgp4/wulfgar.py
sgp4/exporter.py
sgp4/vallado_cpp.cpython-311-darwin.so
sgp4/tcppver.out
sgp4/io.py
sgp4/__init__.py
sgp4/model.py
sgp4/api.py
sgp4/omm.py
sgp4/sample_omm.json
sgp4/propagation.py
sgp4/earth_gravity.py
sgp4/alpha5.py
sgp4/tests.py
sgp4/conveniences.py
sgp4/ext.py
sgp4/sample_omm.xml
