Metadata-Version: 2.1
Name: sgp4
Version: 2.25
Summary: Track Earth satellites given TLE data, using up-to-date 2020 SGP4 routines.
Home-page: https://github.com/brandon-rhodes/python-sgp4
Author: Brandon Rhodes
Author-email: brandon@rhodesmill.org
License: MIT
Classifier: Development Status :: 5 - Production/Stable
Classifier: Intended Audience :: Science/Research
Classifier: License :: OSI Approved :: MIT License
Classifier: Programming Language :: Python :: 2
Classifier: Programming Language :: Python :: 2.7
Classifier: Programming Language :: Python :: 3
Classifier: Programming Language :: Python :: 3.8
Classifier: Programming Language :: Python :: 3.9
Classifier: Programming Language :: Python :: 3.10
Classifier: Programming Language :: Python :: 3.11
Classifier: Programming Language :: Python :: 3.12
Classifier: Programming Language :: Python :: 3.13
Classifier: Topic :: Scientific/Engineering :: Astronomy
Provides: sgp4
License-File: LICENSE
